py_artemis_rgb/__init__.py
py_artemis_rgb/api.py
py_artemis_rgb/artemis.py
py_artemis_rgb/config.py
py_artemis_rgb/exceptions.py
py_artemis_rgb/types.py
py_artemis_rgb/utils.py
py_artemis_rgb-1.0.0.dist-info/METADATA
py_artemis_rgb-1.0.0.dist-info/WHEEL
py_artemis_rgb-1.0.0.dist-info/licenses/LICENSE
py_artemis_rgb-1.0.0.dist-info/RECORD
