Metadata-Version: 2.4
Name: py_artemis_rgb
Version: 1.0.0
Summary: Asynchronous Artemis RGB client
Project-URL: Homepage, https://github.com/etiennec78/py-artemis-rgb
Project-URL: Issues, https://github.com/etiennec78/py-artemis-rgb/issues
Author-email: Etienne Coriou <etienne.coriou@free.fr>
License-File: LICENSE
Classifier: Framework :: AsyncIO
Classifier: Intended Audience :: Developers
Classifier: License :: OSI Approved :: MIT License
Classifier: Operating System :: OS Independent
Classifier: Programming Language :: Python :: 3
Requires-Python: >=3.8
Requires-Dist: aiohttp>=3.8.0
Requires-Dist: pydantic<3.0,>=2.0
